raff/__init__.py
raff/_types.py
raff/cli.py
raff/container.py
raff/stream.py
raff/utils.py
raff-0.1.4.dist-info/licenses/LICENSE
raff-0.1.4.dist-info/METADATA
raff-0.1.4.dist-info/WHEEL
raff-0.1.4.dist-info/entry_points.txt
raff-0.1.4.dist-info/top_level.txt
raff-0.1.4.dist-info/RECORD
