Metadata-Version: 2.4
Name: raff
Version: 0.1.4
Summary: A library and utility for extensive parsing of IFF-based container formats.
License: MIT License
Project-URL: Repository, https://github.com/ubmu/raff
Keywords: iff,riff,rf64,rifx,w64,wave64,bw64,wave
Requires-Python: >=3.11
License-File: LICENSE
Dynamic: license-file
